dojah_client/__init__.py
dojah_client/api_client.py
dojah_client/api_response.py
dojah_client/apis/__init__.py
dojah_client/apis/path_to_api.py
dojah_client/apis/paths/__init__.py
dojah_client/apis/paths/api_v1_aml_screening_info.py
dojah_client/apis/paths/api_v1_aml_screening_platform.py
dojah_client/apis/paths/api_v1_balance.py
dojah_client/apis/paths/api_v1_ca_kyc.py
dojah_client/apis/paths/api_v1_document_analysis.py
dojah_client/apis/paths/api_v1_fraud_ip.py
dojah_client/apis/paths/api_v1_fraud_phone.py
dojah_client/apis/paths/api_v1_fraud_user.py
dojah_client/apis/paths/api_v1_general_account.py
dojah_client/apis/paths/api_v1_gh_kyc_dl.py
dojah_client/apis/paths/api_v1_gh_kyc_passport.py
dojah_client/apis/paths/api_v1_gh_kyc_ssnit.py
dojah_client/apis/paths/api_v1_gh_kyc_voter.py
dojah_client/apis/paths/api_v1_ke_kyc_id.py
dojah_client/apis/paths/api_v1_ke_kyc_passport.py
dojah_client/apis/paths/api_v1_kyb_business_detail.py
dojah_client/apis/paths/api_v1_kyb_business_search.py
dojah_client/apis/paths/api_v1_kyc_accounts.py
dojah_client/apis/paths/api_v1_kyc_address.py
dojah_client/apis/paths/api_v1_kyc_bvn.py
dojah_client/apis/paths/api_v1_kyc_bvn_advance.py
dojah_client/apis/paths/api_v1_kyc_bvn_basic.py
dojah_client/apis/paths/api_v1_kyc_bvn_full.py
dojah_client/apis/paths/api_v1_kyc_cac.py
dojah_client/apis/paths/api_v1_kyc_dl.py
dojah_client/apis/paths/api_v1_kyc_email.py
dojah_client/apis/paths/api_v1_kyc_nin.py
dojah_client/apis/paths/api_v1_kyc_nin_verify.py
dojah_client/apis/paths/api_v1_kyc_nuban.py
dojah_client/apis/paths/api_v1_kyc_nuban_bvn.py
dojah_client/apis/paths/api_v1_kyc_passport.py
dojah_client/apis/paths/api_v1_kyc_phone_number.py
dojah_client/apis/paths/api_v1_kyc_phone_number_basic.py
dojah_client/apis/paths/api_v1_kyc_photoid_verify.py
dojah_client/apis/paths/api_v1_kyc_tin.py
dojah_client/apis/paths/api_v1_kyc_vin.py
dojah_client/apis/paths/api_v1_kyc_vnin.py
dojah_client/apis/paths/api_v1_kyc_vnin_verify.py
dojah_python_sdk-4.1.0.dist-info/LICENSE
dojah_python_sdk-4.1.0.dist-info/METADATA
dojah_python_sdk-4.1.0.dist-info/WHEEL
dojah_python_sdk-4.1.0.dist-info/RECORD
